{
 "id": "2415180",
 "temporada": "2024",
 "grupo": "E-B",
 "jornada": "Jornada 1(13/10/2024)",
 "equipoLocal": {
  "id": "950778",
  "nombre": "LUCENTUM ALICANTE"
 },
 "equipoVisitante": {
  "id": "950873",
  "nombre": "ADESAVI A"
 },
 "resultado": "59-65",
 "disputado": true,
 "descargado": "2026-07-17T09:22:05.149Z",
 "boxscore": {
  "local": [
   {
    "idJugador": "2087557",
    "titular": false,
    "dorsal": "0",
    "nombre": "MUÑOZ PALENCIA, JESUS",
    "seg": 616,
    "pt": 3,
    "t2": {
     "a": 1,
     "i": 1
    },
    "t3": {
     "a": 0,
     "i": 2
    },
    "tc": {
     "a": 1,
     "i": 3
    },
    "tl": {
     "a": 1,
     "i": 2
    },
    "ro": 0,
    "rd": 2,
    "rt": 2,
    "as": 2,
    "br": 0,
    "bp": 0,
    "tf": 0,
    "tco": 0,
    "mt": 0,
    "fc": 2,
    "fr": 1,
    "va": 3,
    "pm": 3
   },
   {
    "idJugador": "2557720",
    "titular": true,
    "dorsal": "2",
    "nombre": "GARCIA ROSELLO, MARCOS",
    "seg": 1572,
    "pt": 12,
    "t2": {
     "a": 3,
     "i": 7
    },
    "t3": {
     "a": 1,
     "i": 6
    },
    "tc": {
     "a": 4,
     "i": 13
    },
    "tl": {
     "a": 3,
     "i": 6
    },
    "ro": 2,
    "rd": 6,
    "rt": 8,
    "as": 0,
    "br": 0,
    "bp": 2,
    "tf": 1,
    "tco": 0,
    "mt": 1,
    "fc": 4,
    "fr": 3,
    "va": 6,
    "pm": 8
   },
   {
    "idJugador": "1900423",
    "titular": true,
    "dorsal": "3",
    "nombre": "GALVEZ ARROYO, SAMUEL",
    "seg": 1308,
    "pt": 7,
    "t2": {
     "a": 3,
     "i": 5
    },
    "t3": {
     "a": 0,
     "i": 3
    },
    "tc": {
     "a": 3,
     "i": 8
    },
    "tl": {
     "a": 1,
     "i": 6
    },
    "ro": 2,
    "rd": 6,
    "rt": 8,
    "as": 3,
    "br": 1,
    "bp": 2,
    "tf": 0,
    "tco": 0,
    "mt": 0,
    "fc": 4,
    "fr": 6,
    "va": 9,
    "pm": -25
   },
   {
    "idJugador": "2183928",
    "titular": false,
    "dorsal": "4",
    "nombre": "CASTRILLON RODRIGUEZ, OSCAR",
    "seg": 1004,
    "pt": 4,
    "t2": {
     "a": 2,
     "i": 6
    },
    "t3": {
     "a": 0,
     "i": 1
    },
    "tc": {
     "a": 2,
     "i": 7
    },
    "tl": {
     "a": 0,
     "i": 0
    },
    "ro": 0,
    "rd": 1,
    "rt": 1,
    "as": 0,
    "br": 1,
    "bp": 0,
    "tf": 1,
    "tco": 0,
    "mt": 0,
    "fc": 1,
    "fr": 1,
    "va": 2,
    "pm": -3
   },
   {
    "idJugador": "1900426",
    "titular": true,
    "dorsal": "8",
    "nombre": "GALVEZ ARROYO, VICTOR",
    "seg": 1293,
    "pt": 2,
    "t2": {
     "a": 0,
     "i": 1
    },
    "t3": {
     "a": 0,
     "i": 1
    },
    "tc": {
     "a": 0,
     "i": 2
    },
    "tl": {
     "a": 2,
     "i": 4
    },
    "ro": 0,
    "rd": 7,
    "rt": 7,
    "as": 2,
    "br": 1,
    "bp": 2,
    "tf": 0,
    "tco": 0,
    "mt": 0,
    "fc": 4,
    "fr": 3,
    "va": 5,
    "pm": -7
   },
   {
    "idJugador": "2027626",
    "titular": true,
    "dorsal": "9",
    "nombre": "TUDELA GARCIA, GUSTAVO",
    "seg": 1338,
    "pt": 6,
    "t2": {
     "a": 2,
     "i": 3
    },
    "t3": {
     "a": 0,
     "i": 0
    },
    "tc": {
     "a": 2,
     "i": 3
    },
    "tl": {
     "a": 2,
     "i": 4
    },
    "ro": 2,
    "rd": 1,
    "rt": 3,
    "as": 0,
    "br": 2,
    "bp": 0,
    "tf": 0,
    "tco": 0,
    "mt": 0,
    "fc": 3,
    "fr": 2,
    "va": 7,
    "pm": -7
   },
   {
    "idJugador": "2141015",
    "titular": false,
    "dorsal": "10",
    "nombre": "GADEA VALENCIA, VICTOR",
    "seg": 800,
    "pt": 3,
    "t2": {
     "a": 1,
     "i": 1
    },
    "t3": {
     "a": 0,
     "i": 0
    },
    "tc": {
     "a": 1,
     "i": 1
    },
    "tl": {
     "a": 1,
     "i": 2
    },
    "ro": 0,
    "rd": 0,
    "rt": 0,
    "as": 0,
    "br": 0,
    "bp": 1,
    "tf": 0,
    "tco": 0,
    "mt": 0,
    "fc": 3,
    "fr": 1,
    "va": -1,
    "pm": 6
   },
   {
    "idJugador": "2117260",
    "titular": false,
    "dorsal": "14",
    "nombre": "SABATER MARTINEZ, GERMAN",
    "seg": 935,
    "pt": 2,
    "t2": {
     "a": 1,
     "i": 2
    },
    "t3": {
     "a": 0,
     "i": 1
    },
    "tc": {
     "a": 1,
     "i": 3
    },
    "tl": {
     "a": 0,
     "i": 0
    },
    "ro": 0,
    "rd": 5,
    "rt": 5,
    "as": 0,
    "br": 0,
    "bp": 0,
    "tf": 0,
    "tco": 0,
    "mt": 0,
    "fc": 2,
    "fr": 0,
    "va": 3,
    "pm": -10
   },
   {
    "idJugador": "2265449",
    "titular": false,
    "dorsal": "15",
    "nombre": "VERDU SCHLIE, PAUL",
    "seg": 1343,
    "pt": 4,
    "t2": {
     "a": 1,
     "i": 4
    },
    "t3": {
     "a": 0,
     "i": 1
    },
    "tc": {
     "a": 1,
     "i": 5
    },
    "tl": {
     "a": 2,
     "i": 2
    },
    "ro": 1,
    "rd": 0,
    "rt": 1,
    "as": 2,
    "br": 0,
    "bp": 1,
    "tf": 0,
    "tco": 1,
    "mt": 0,
    "fc": 0,
    "fr": 1,
    "va": 3,
    "pm": 5
   },
   {
    "idJugador": "2112479",
    "titular": false,
    "dorsal": "25",
    "nombre": "FERRIZ SELLES, ALBERTO",
    "seg": 238,
    "pt": 0,
    "t2": {
     "a": 0,
     "i": 0
    },
    "t3": {
     "a": 0,
     "i": 0
    },
    "tc": {
     "a": 0,
     "i": 0
    },
    "tl": {
     "a": 0,
     "i": 0
    },
    "ro": 1,
    "rd": 1,
    "rt": 2,
    "as": 0,
    "br": 0,
    "bp": 0,
    "tf": 0,
    "tco": 0,
    "mt": 0,
    "fc": 1,
    "fr": 0,
    "va": 1,
    "pm": -5
   },
   {
    "idJugador": "2221478",
    "titular": true,
    "dorsal": "42",
    "nombre": "KLOTZ MAROTO, CONRAD",
    "seg": 1553,
    "pt": 16,
    "t2": {
     "a": 4,
     "i": 8
    },
    "t3": {
     "a": 0,
     "i": 4
    },
    "tc": {
     "a": 4,
     "i": 12
    },
    "tl": {
     "a": 8,
     "i": 11
    },
    "ro": 0,
    "rd": 5,
    "rt": 5,
    "as": 3,
    "br": 1,
    "bp": 3,
    "tf": 0,
    "tco": 0,
    "mt": 0,
    "fc": 3,
    "fr": 6,
    "va": 14,
    "pm": 5
   }
  ],
  "visitante": [
   {
    "idJugador": "2006599",
    "titular": false,
    "dorsal": "2",
    "nombre": "OSA NZANG, LUCIANO",
    "seg": 362,
    "pt": 0,
    "t2": {
     "a": 0,
     "i": 1
    },
    "t3": {
     "a": 0,
     "i": 0
    },
    "tc": {
     "a": 0,
     "i": 1
    },
    "tl": {
     "a": 0,
     "i": 4
    },
    "ro": 1,
    "rd": 0,
    "rt": 1,
    "as": 0,
    "br": 0,
    "bp": 0,
    "tf": 0,
    "tco": 0,
    "mt": 0,
    "fc": 1,
    "fr": 2,
    "va": -3,
    "pm": -7
   },
   {
    "idJugador": "2077062",
    "titular": true,
    "dorsal": "4",
    "nombre": "PORRA MAESTRE, JOEL",
    "seg": 786,
    "pt": 0,
    "t2": {
     "a": 0,
     "i": 2
    },
    "t3": {
     "a": 0,
     "i": 1
    },
    "tc": {
     "a": 0,
     "i": 3
    },
    "tl": {
     "a": 0,
     "i": 0
    },
    "ro": 0,
    "rd": 0,
    "rt": 0,
    "as": 0,
    "br": 0,
    "bp": 1,
    "tf": 0,
    "tco": 0,
    "mt": 0,
    "fc": 2,
    "fr": 1,
    "va": -5,
    "pm": 8
   },
   {
    "idJugador": "1794812",
    "titular": false,
    "dorsal": "7",
    "nombre": "BARTUAL BARDISA, OSCAR",
    "seg": 676,
    "pt": 4,
    "t2": {
     "a": 2,
     "i": 3
    },
    "t3": {
     "a": 0,
     "i": 4
    },
    "tc": {
     "a": 2,
     "i": 7
    },
    "tl": {
     "a": 0,
     "i": 0
    },
    "ro": 2,
    "rd": 2,
    "rt": 4,
    "as": 0,
    "br": 0,
    "bp": 0,
    "tf": 0,
    "tco": 0,
    "mt": 0,
    "fc": 2,
    "fr": 1,
    "va": 2,
    "pm": -8
   },
   {
    "idJugador": "1698706",
    "titular": false,
    "dorsal": "8",
    "nombre": "COMINO DIEZ, CARLOS",
    "seg": 787,
    "pt": 2,
    "t2": {
     "a": 0,
     "i": 1
    },
    "t3": {
     "a": 0,
     "i": 3
    },
    "tc": {
     "a": 0,
     "i": 4
    },
    "tl": {
     "a": 2,
     "i": 2
    },
    "ro": 2,
    "rd": 0,
    "rt": 2,
    "as": 0,
    "br": 0,
    "bp": 0,
    "tf": 0,
    "tco": 1,
    "mt": 0,
    "fc": 1,
    "fr": 1,
    "va": 0,
    "pm": -22
   },
   {
    "idJugador": "1677187",
    "titular": true,
    "dorsal": "10",
    "nombre": "SERNEGUET GARVI, ALDO JOSE",
    "seg": 1951,
    "pt": 16,
    "t2": {
     "a": 2,
     "i": 4
    },
    "t3": {
     "a": 2,
     "i": 4
    },
    "tc": {
     "a": 4,
     "i": 8
    },
    "tl": {
     "a": 6,
     "i": 11
    },
    "ro": 1,
    "rd": 9,
    "rt": 10,
    "as": 6,
    "br": 4,
    "bp": 3,
    "tf": 0,
    "tco": 0,
    "mt": 0,
    "fc": 3,
    "fr": 10,
    "va": 31,
    "pm": 16
   },
   {
    "idJugador": "1796561",
    "titular": true,
    "dorsal": "12",
    "nombre": "ALBALADEJO PEREZ, NORBERTO",
    "seg": 1607,
    "pt": 14,
    "t2": {
     "a": 7,
     "i": 16
    },
    "t3": {
     "a": 0,
     "i": 8
    },
    "tc": {
     "a": 7,
     "i": 24
    },
    "tl": {
     "a": 0,
     "i": 1
    },
    "ro": 1,
    "rd": 2,
    "rt": 3,
    "as": 1,
    "br": 1,
    "bp": 0,
    "tf": 0,
    "tco": 0,
    "mt": 0,
    "fc": 4,
    "fr": 2,
    "va": -1,
    "pm": 22
   },
   {
    "idJugador": "1876136",
    "titular": true,
    "dorsal": "14",
    "nombre": "STRUKOV STRUKOV, VALENTIN",
    "seg": 1890,
    "pt": 15,
    "t2": {
     "a": 6,
     "i": 8
    },
    "t3": {
     "a": 0,
     "i": 1
    },
    "tc": {
     "a": 6,
     "i": 9
    },
    "tl": {
     "a": 3,
     "i": 5
    },
    "ro": 4,
    "rd": 11,
    "rt": 15,
    "as": 1,
    "br": 0,
    "bp": 3,
    "tf": 0,
    "tco": 0,
    "mt": 0,
    "fc": 2,
    "fr": 5,
    "va": 26,
    "pm": 14
   },
   {
    "idJugador": "1294535",
    "titular": false,
    "dorsal": "15",
    "nombre": "MOLINELLI VILLALBA, GABRIEL",
    "seg": 587,
    "pt": 0,
    "t2": {
     "a": 0,
     "i": 3
    },
    "t3": {
     "a": 0,
     "i": 0
    },
    "tc": {
     "a": 0,
     "i": 3
    },
    "tl": {
     "a": 0,
     "i": 0
    },
    "ro": 3,
    "rd": 1,
    "rt": 4,
    "as": 0,
    "br": 0,
    "bp": 1,
    "tf": 1,
    "tco": 0,
    "mt": 0,
    "fc": 1,
    "fr": 2,
    "va": 2,
    "pm": -11
   },
   {
    "idJugador": "1208481",
    "titular": true,
    "dorsal": "16",
    "nombre": "SANCHEZ LUBIAN, PEDRO MANUEL",
    "seg": 1523,
    "pt": 10,
    "t2": {
     "a": 3,
     "i": 4
    },
    "t3": {
     "a": 1,
     "i": 8
    },
    "tc": {
     "a": 4,
     "i": 12
    },
    "tl": {
     "a": 1,
     "i": 2
    },
    "ro": 4,
    "rd": 1,
    "rt": 5,
    "as": 2,
    "br": 0,
    "bp": 1,
    "tf": 0,
    "tco": 1,
    "mt": 0,
    "fc": 3,
    "fr": 2,
    "va": 6,
    "pm": 17
   },
   {
    "idJugador": "2020015",
    "titular": false,
    "dorsal": "24",
    "nombre": "SEVERA LENCINA, CARLOS",
    "seg": 1192,
    "pt": 4,
    "t2": {
     "a": 0,
     "i": 1
    },
    "t3": {
     "a": 1,
     "i": 2
    },
    "tc": {
     "a": 1,
     "i": 3
    },
    "tl": {
     "a": 1,
     "i": 2
    },
    "ro": 1,
    "rd": 0,
    "rt": 1,
    "as": 1,
    "br": 1,
    "bp": 0,
    "tf": 0,
    "tco": 0,
    "mt": 0,
    "fc": 3,
    "fr": 1,
    "va": 2,
    "pm": 19
   },
   {
    "idJugador": "1605745",
    "titular": false,
    "dorsal": "30",
    "nombre": "SANCHEZ ALIAGA, OLIVER",
    "seg": 470,
    "pt": 0,
    "t2": {
     "a": 0,
     "i": 0
    },
    "t3": {
     "a": 0,
     "i": 1
    },
    "tc": {
     "a": 0,
     "i": 1
    },
    "tl": {
     "a": 0,
     "i": 0
    },
    "ro": 1,
    "rd": 1,
    "rt": 2,
    "as": 2,
    "br": 0,
    "bp": 1,
    "tf": 0,
    "tco": 0,
    "mt": 0,
    "fc": 1,
    "fr": 0,
    "va": 1,
    "pm": -18
   },
   {
    "idJugador": "2071571",
    "titular": false,
    "dorsal": "37",
    "nombre": "MIRANDA ORTEGA, JORGE",
    "seg": 169,
    "pt": 0,
    "t2": {
     "a": 0,
     "i": 0
    },
    "t3": {
     "a": 0,
     "i": 0
    },
    "tc": {
     "a": 0,
     "i": 0
    },
    "tl": {
     "a": 0,
     "i": 0
    },
    "ro": 0,
    "rd": 0,
    "rt": 0,
    "as": 0,
    "br": 0,
    "bp": 0,
    "tf": 0,
    "tco": 0,
    "mt": 0,
    "fc": 2,
    "fr": 0,
    "va": -2,
    "pm": 0
   }
  ],
  "cuartos": [
   {
    "periodo": "1º C",
    "local": 17,
    "visitante": 18
   },
   {
    "periodo": "2º C",
    "local": 11,
    "visitante": 21
   },
   {
    "periodo": "3º C",
    "local": 22,
    "visitante": 9
   },
   {
    "periodo": "4º C",
    "local": 9,
    "visitante": 17
   }
  ]
 }
}