{
 "id": "2484724",
 "temporada": "2025",
 "grupo": "E-B",
 "jornada": "Jornada 3(19/10/2025)",
 "equipoLocal": {
  "id": "979993",
  "nombre": "SERVIGROUP BENIDORM"
 },
 "equipoVisitante": {
  "id": "981147",
  "nombre": "C.A. MONTEMAR"
 },
 "resultado": "60-40",
 "disputado": true,
 "descargado": "2026-07-17T07:21:30.244Z",
 "boxscore": {
  "local": [
   {
    "idJugador": "2375675",
    "titular": true,
    "dorsal": "1",
    "nombre": "AGBEKO, REGINALD CALEB",
    "seg": 1190,
    "pt": 8,
    "t2": {
     "a": 3,
     "i": 11
    },
    "t3": {
     "a": 0,
     "i": 0
    },
    "tc": {
     "a": 3,
     "i": 11
    },
    "tl": {
     "a": 2,
     "i": 2
    },
    "ro": 4,
    "rd": 3,
    "rt": 7,
    "as": 1,
    "br": 2,
    "bp": 2,
    "tf": 0,
    "tco": 0,
    "mt": 0,
    "fc": 4,
    "fr": 1,
    "va": 5,
    "pm": 9
   },
   {
    "idJugador": "2817550",
    "titular": true,
    "dorsal": "2",
    "nombre": "DESPLACE, THIBAULT PIERRE ROBERT",
    "seg": 1452,
    "pt": 6,
    "t2": {
     "a": 3,
     "i": 5
    },
    "t3": {
     "a": 0,
     "i": 2
    },
    "tc": {
     "a": 3,
     "i": 7
    },
    "tl": {
     "a": 0,
     "i": 1
    },
    "ro": 0,
    "rd": 7,
    "rt": 7,
    "as": 3,
    "br": 1,
    "bp": 3,
    "tf": 0,
    "tco": 0,
    "mt": 0,
    "fc": 1,
    "fr": 4,
    "va": 12,
    "pm": 5
   },
   {
    "idJugador": "2820173",
    "titular": false,
    "dorsal": "3",
    "nombre": "MARZIALI, MATEO",
    "seg": 1687,
    "pt": 4,
    "t2": {
     "a": 2,
     "i": 5
    },
    "t3": {
     "a": 0,
     "i": 2
    },
    "tc": {
     "a": 2,
     "i": 7
    },
    "tl": {
     "a": 0,
     "i": 0
    },
    "ro": 0,
    "rd": 7,
    "rt": 7,
    "as": 2,
    "br": 2,
    "bp": 5,
    "tf": 0,
    "tco": 0,
    "mt": 0,
    "fc": 3,
    "fr": 5,
    "va": 7,
    "pm": 6
   },
   {
    "idJugador": "2798073",
    "titular": false,
    "dorsal": "6",
    "nombre": "DAMULEVICIUS, SIDAS",
    "seg": 295,
    "pt": 2,
    "t2": {
     "a": 1,
     "i": 1
    },
    "t3": {
     "a": 0,
     "i": 0
    },
    "tc": {
     "a": 1,
     "i": 1
    },
    "tl": {
     "a": 0,
     "i": 0
    },
    "ro": 0,
    "rd": 0,
    "rt": 0,
    "as": 0,
    "br": 0,
    "bp": 0,
    "tf": 0,
    "tco": 0,
    "mt": 0,
    "fc": 0,
    "fr": 0,
    "va": 2,
    "pm": 5
   },
   {
    "idJugador": "1756269",
    "titular": false,
    "dorsal": "8",
    "nombre": "CAZORLA ZARAGOZI, DARIO",
    "seg": 1390,
    "pt": 5,
    "t2": {
     "a": 0,
     "i": 2
    },
    "t3": {
     "a": 1,
     "i": 4
    },
    "tc": {
     "a": 1,
     "i": 6
    },
    "tl": {
     "a": 2,
     "i": 2
    },
    "ro": 0,
    "rd": 3,
    "rt": 3,
    "as": 2,
    "br": 2,
    "bp": 1,
    "tf": 0,
    "tco": 0,
    "mt": 0,
    "fc": 3,
    "fr": 2,
    "va": 5,
    "pm": 20
   },
   {
    "idJugador": "1208733",
    "titular": false,
    "dorsal": "10",
    "nombre": "ORTOLA TOMAS, JOAN MARIA",
    "seg": 853,
    "pt": 4,
    "t2": {
     "a": 2,
     "i": 3
    },
    "t3": {
     "a": 0,
     "i": 1
    },
    "tc": {
     "a": 2,
     "i": 4
    },
    "tl": {
     "a": 0,
     "i": 0
    },
    "ro": 1,
    "rd": 4,
    "rt": 5,
    "as": 0,
    "br": 1,
    "bp": 1,
    "tf": 0,
    "tco": 0,
    "mt": 0,
    "fc": 3,
    "fr": 1,
    "va": 5,
    "pm": 11
   },
   {
    "idJugador": "1995485",
    "titular": true,
    "dorsal": "11",
    "nombre": "JIMENA LLORCA, SERGIO PATRIZIO",
    "seg": 1603,
    "pt": 2,
    "t2": {
     "a": 1,
     "i": 5
    },
    "t3": {
     "a": 0,
     "i": 4
    },
    "tc": {
     "a": 1,
     "i": 9
    },
    "tl": {
     "a": 0,
     "i": 2
    },
    "ro": 3,
    "rd": 1,
    "rt": 4,
    "as": 1,
    "br": 3,
    "bp": 0,
    "tf": 0,
    "tco": 0,
    "mt": 0,
    "fc": 2,
    "fr": 2,
    "va": 0,
    "pm": 8
   },
   {
    "idJugador": "2378721",
    "titular": false,
    "dorsal": "22",
    "nombre": "SIDDIQUE, SALEEM",
    "seg": 1059,
    "pt": 2,
    "t2": {
     "a": 1,
     "i": 3
    },
    "t3": {
     "a": 0,
     "i": 1
    },
    "tc": {
     "a": 1,
     "i": 4
    },
    "tl": {
     "a": 0,
     "i": 2
    },
    "ro": 1,
    "rd": 2,
    "rt": 3,
    "as": 0,
    "br": 0,
    "bp": 1,
    "tf": 0,
    "tco": 0,
    "mt": 0,
    "fc": 2,
    "fr": 1,
    "va": -2,
    "pm": 8
   },
   {
    "idJugador": "1994360",
    "titular": true,
    "dorsal": "24",
    "nombre": "ZAMORA MAÑA, UNAI",
    "seg": 1070,
    "pt": 16,
    "t2": {
     "a": 4,
     "i": 6
    },
    "t3": {
     "a": 2,
     "i": 6
    },
    "tc": {
     "a": 6,
     "i": 12
    },
    "tl": {
     "a": 2,
     "i": 2
    },
    "ro": 3,
    "rd": 5,
    "rt": 8,
    "as": 1,
    "br": 2,
    "bp": 1,
    "tf": 0,
    "tco": 0,
    "mt": 0,
    "fc": 2,
    "fr": 2,
    "va": 20,
    "pm": 14
   },
   {
    "idJugador": "1508383",
    "titular": true,
    "dorsal": "33",
    "nombre": "KLEINJAN RODRIGUEZ, ALAN PETER",
    "seg": 1401,
    "pt": 11,
    "t2": {
     "a": 4,
     "i": 5
    },
    "t3": {
     "a": 1,
     "i": 5
    },
    "tc": {
     "a": 5,
     "i": 10
    },
    "tl": {
     "a": 0,
     "i": 0
    },
    "ro": 0,
    "rd": 4,
    "rt": 4,
    "as": 0,
    "br": 3,
    "bp": 3,
    "tf": 0,
    "tco": 0,
    "mt": 0,
    "fc": 1,
    "fr": 1,
    "va": 10,
    "pm": 14
   }
  ],
  "visitante": [
   {
    "idJugador": "1792737",
    "titular": false,
    "dorsal": "4",
    "nombre": "ALFEREZ CANSECO, DIEGO",
    "seg": 623,
    "pt": 4,
    "t2": {
     "a": 2,
     "i": 2
    },
    "t3": {
     "a": 0,
     "i": 1
    },
    "tc": {
     "a": 2,
     "i": 3
    },
    "tl": {
     "a": 0,
     "i": 0
    },
    "ro": 2,
    "rd": 2,
    "rt": 4,
    "as": 0,
    "br": 0,
    "bp": 0,
    "tf": 0,
    "tco": 0,
    "mt": 0,
    "fc": 0,
    "fr": 0,
    "va": 7,
    "pm": -4
   },
   {
    "idJugador": "1889731",
    "titular": true,
    "dorsal": "7",
    "nombre": "MARTIN MARTINEZ, MARCOS",
    "seg": 1109,
    "pt": 1,
    "t2": {
     "a": 0,
     "i": 0
    },
    "t3": {
     "a": 0,
     "i": 0
    },
    "tc": {
     "a": 0,
     "i": 0
    },
    "tl": {
     "a": 1,
     "i": 2
    },
    "ro": 5,
    "rd": 3,
    "rt": 8,
    "as": 2,
    "br": 6,
    "bp": 3,
    "tf": 0,
    "tco": 0,
    "mt": 0,
    "fc": 3,
    "fr": 2,
    "va": 12,
    "pm": -2
   },
   {
    "idJugador": "2377174",
    "titular": false,
    "dorsal": "8",
    "nombre": "CASTELLANOS MARTINEZ, CRISTIAN",
    "seg": 117,
    "pt": 0,
    "t2": {
     "a": 0,
     "i": 0
    },
    "t3": {
     "a": 0,
     "i": 2
    },
    "tc": {
     "a": 0,
     "i": 2
    },
    "tl": {
     "a": 0,
     "i": 0
    },
    "ro": 0,
    "rd": 0,
    "rt": 0,
    "as": 0,
    "br": 0,
    "bp": 0,
    "tf": 0,
    "tco": 0,
    "mt": 0,
    "fc": 0,
    "fr": 0,
    "va": -2,
    "pm": 3
   },
   {
    "idJugador": "343549",
    "titular": false,
    "dorsal": "12",
    "nombre": "GARCIA NAVEA, JORGE",
    "seg": 1473,
    "pt": 7,
    "t2": {
     "a": 2,
     "i": 3
    },
    "t3": {
     "a": 1,
     "i": 4
    },
    "tc": {
     "a": 3,
     "i": 7
    },
    "tl": {
     "a": 0,
     "i": 1
    },
    "ro": 1,
    "rd": 4,
    "rt": 5,
    "as": 2,
    "br": 1,
    "bp": 3,
    "tf": 0,
    "tco": 0,
    "mt": 0,
    "fc": 1,
    "fr": 1,
    "va": 7,
    "pm": -15
   },
   {
    "idJugador": "2275702",
    "titular": false,
    "dorsal": "13",
    "nombre": "TERREROS RIVAS, BEÑAT",
    "seg": 1280,
    "pt": 2,
    "t2": {
     "a": 1,
     "i": 7
    },
    "t3": {
     "a": 0,
     "i": 3
    },
    "tc": {
     "a": 1,
     "i": 10
    },
    "tl": {
     "a": 0,
     "i": 0
    },
    "ro": 0,
    "rd": 1,
    "rt": 1,
    "as": 0,
    "br": 1,
    "bp": 1,
    "tf": 0,
    "tco": 0,
    "mt": 0,
    "fc": 1,
    "fr": 0,
    "va": -7,
    "pm": -16
   },
   {
    "idJugador": "1526593",
    "titular": true,
    "dorsal": "15",
    "nombre": "NÚÑEZ NIEVAS, JUAN JOSÉ",
    "seg": 1056,
    "pt": 3,
    "t2": {
     "a": 0,
     "i": 4
    },
    "t3": {
     "a": 1,
     "i": 3
    },
    "tc": {
     "a": 1,
     "i": 7
    },
    "tl": {
     "a": 0,
     "i": 0
    },
    "ro": 0,
    "rd": 2,
    "rt": 2,
    "as": 0,
    "br": 2,
    "bp": 2,
    "tf": 0,
    "tco": 0,
    "mt": 0,
    "fc": 3,
    "fr": 3,
    "va": -1,
    "pm": -5
   },
   {
    "idJugador": "2021078",
    "titular": false,
    "dorsal": "22",
    "nombre": "GARCIA CARCASES, GUSTAVO",
    "seg": 1028,
    "pt": 2,
    "t2": {
     "a": 1,
     "i": 3
    },
    "t3": {
     "a": 0,
     "i": 4
    },
    "tc": {
     "a": 1,
     "i": 7
    },
    "tl": {
     "a": 0,
     "i": 4
    },
    "ro": 1,
    "rd": 5,
    "rt": 6,
    "as": 1,
    "br": 2,
    "bp": 1,
    "tf": 0,
    "tco": 0,
    "mt": 0,
    "fc": 4,
    "fr": 3,
    "va": -1,
    "pm": -14
   },
   {
    "idJugador": "2758847",
    "titular": false,
    "dorsal": "26",
    "nombre": "DAMESTOY, MATTIN",
    "seg": 203,
    "pt": 0,
    "t2": {
     "a": 0,
     "i": 0
    },
    "t3": {
     "a": 0,
     "i": 0
    },
    "tc": {
     "a": 0,
     "i": 0
    },
    "tl": {
     "a": 0,
     "i": 0
    },
    "ro": 0,
    "rd": 0,
    "rt": 0,
    "as": 0,
    "br": 0,
    "bp": 1,
    "tf": 0,
    "tco": 0,
    "mt": 0,
    "fc": 0,
    "fr": 0,
    "va": -1,
    "pm": -8
   },
   {
    "idJugador": "2739766",
    "titular": true,
    "dorsal": "34",
    "nombre": "ANZULUNI, MLETSHI YANNICK",
    "seg": 1649,
    "pt": 14,
    "t2": {
     "a": 3,
     "i": 6
    },
    "t3": {
     "a": 2,
     "i": 7
    },
    "tc": {
     "a": 5,
     "i": 13
    },
    "tl": {
     "a": 2,
     "i": 4
    },
    "ro": 2,
    "rd": 10,
    "rt": 12,
    "as": 0,
    "br": 0,
    "bp": 8,
    "tf": 0,
    "tco": 0,
    "mt": 0,
    "fc": 3,
    "fr": 4,
    "va": 9,
    "pm": -16
   },
   {
    "idJugador": "1854909",
    "titular": false,
    "dorsal": "44",
    "nombre": "GILABERT FERRI, CARLOS",
    "seg": 611,
    "pt": 0,
    "t2": {
     "a": 0,
     "i": 0
    },
    "t3": {
     "a": 0,
     "i": 0
    },
    "tc": {
     "a": 0,
     "i": 0
    },
    "tl": {
     "a": 0,
     "i": 0
    },
    "ro": 1,
    "rd": 1,
    "rt": 2,
    "as": 0,
    "br": 1,
    "bp": 1,
    "tf": 0,
    "tco": 0,
    "mt": 0,
    "fc": 0,
    "fr": 1,
    "va": 3,
    "pm": -3
   },
   {
    "idJugador": "1673632",
    "titular": true,
    "dorsal": "57",
    "nombre": "FERNANDEZ CARRASCO, MATEO",
    "seg": 1598,
    "pt": 4,
    "t2": {
     "a": 1,
     "i": 5
    },
    "t3": {
     "a": 0,
     "i": 3
    },
    "tc": {
     "a": 1,
     "i": 8
    },
    "tl": {
     "a": 2,
     "i": 6
    },
    "ro": 1,
    "rd": 2,
    "rt": 3,
    "as": 1,
    "br": 1,
    "bp": 2,
    "tf": 0,
    "tco": 0,
    "mt": 0,
    "fc": 1,
    "fr": 6,
    "va": 1,
    "pm": -14
   },
   {
    "idJugador": "2188694",
    "titular": true,
    "dorsal": "89",
    "nombre": "ZHENG, BOLONG",
    "seg": 1253,
    "pt": 3,
    "t2": {
     "a": 0,
     "i": 0
    },
    "t3": {
     "a": 1,
     "i": 6
    },
    "tc": {
     "a": 1,
     "i": 6
    },
    "tl": {
     "a": 0,
     "i": 0
    },
    "ro": 0,
    "rd": 3,
    "rt": 3,
    "as": 1,
    "br": 0,
    "bp": 1,
    "tf": 0,
    "tco": 0,
    "mt": 0,
    "fc": 3,
    "fr": 0,
    "va": -2,
    "pm": -6
   }
  ],
  "cuartos": [
   {
    "periodo": "1º C",
    "local": 24,
    "visitante": 15
   },
   {
    "periodo": "2º C",
    "local": 14,
    "visitante": 9
   },
   {
    "periodo": "3º C",
    "local": 14,
    "visitante": 10
   },
   {
    "periodo": "4º C",
    "local": 8,
    "visitante": 6
   }
  ]
 }
}