{
 "id": "2488161",
 "temporada": "2025",
 "grupo": "D-B",
 "jornada": "Jornada 6(09/11/2025)",
 "equipoLocal": {
  "id": "979904",
  "nombre": "BOSCO MÉRIDA PATRIMONIO DE LA HUMANIDAD"
 },
 "equipoVisitante": {
  "id": "981511",
  "nombre": "INSOLAC CB ALCALÁ CAJA87"
 },
 "resultado": "65-83",
 "disputado": true,
 "descargado": "2026-07-17T07:07:34.121Z",
 "boxscore": {
  "local": [
   {
    "idJugador": "2816298",
    "titular": true,
    "dorsal": "1",
    "nombre": "ANDRADE, EDNILSON LUIS AGUIAR",
    "seg": 1308,
    "pt": 3,
    "t2": {
     "a": 0,
     "i": 3
    },
    "t3": {
     "a": 1,
     "i": 5
    },
    "tc": {
     "a": 1,
     "i": 8
    },
    "tl": {
     "a": 0,
     "i": 0
    },
    "ro": 4,
    "rd": 6,
    "rt": 10,
    "as": 2,
    "br": 1,
    "bp": 4,
    "tf": 0,
    "tco": 0,
    "mt": 0,
    "fc": 3,
    "fr": 1,
    "va": 3,
    "pm": -9
   },
   {
    "idJugador": "1603172",
    "titular": true,
    "dorsal": "7",
    "nombre": "GARRIDO SOTO, FRANCISCO JAVIER",
    "seg": 1298,
    "pt": 6,
    "t2": {
     "a": 3,
     "i": 5
    },
    "t3": {
     "a": 0,
     "i": 0
    },
    "tc": {
     "a": 3,
     "i": 5
    },
    "tl": {
     "a": 0,
     "i": 3
    },
    "ro": 2,
    "rd": 1,
    "rt": 3,
    "as": 1,
    "br": 3,
    "bp": 2,
    "tf": 0,
    "tco": 1,
    "mt": 0,
    "fc": 0,
    "fr": 3,
    "va": 9,
    "pm": 0
   },
   {
    "idJugador": "2816301",
    "titular": true,
    "dorsal": "8",
    "nombre": "RICARDO, JUSCELINO MANUEL",
    "seg": 2003,
    "pt": 17,
    "t2": {
     "a": 4,
     "i": 8
    },
    "t3": {
     "a": 1,
     "i": 5
    },
    "tc": {
     "a": 5,
     "i": 13
    },
    "tl": {
     "a": 6,
     "i": 7
    },
    "ro": 0,
    "rd": 3,
    "rt": 3,
    "as": 0,
    "br": 6,
    "bp": 2,
    "tf": 0,
    "tco": 1,
    "mt": 3,
    "fc": 1,
    "fr": 7,
    "va": 21,
    "pm": -10
   },
   {
    "idJugador": "2019554",
    "titular": false,
    "dorsal": "9",
    "nombre": "PINILLA NUÑEZ, JAVIER",
    "seg": 1397,
    "pt": 18,
    "t2": {
     "a": 1,
     "i": 4
    },
    "t3": {
     "a": 3,
     "i": 5
    },
    "tc": {
     "a": 4,
     "i": 9
    },
    "tl": {
     "a": 7,
     "i": 8
    },
    "ro": 3,
    "rd": 4,
    "rt": 7,
    "as": 1,
    "br": 1,
    "bp": 4,
    "tf": 0,
    "tco": 0,
    "mt": 0,
    "fc": 2,
    "fr": 6,
    "va": 21,
    "pm": -15
   },
   {
    "idJugador": "1823183",
    "titular": false,
    "dorsal": "19",
    "nombre": "MOLINA LOPEZ, MANUEL",
    "seg": 559,
    "pt": 2,
    "t2": {
     "a": 1,
     "i": 1
    },
    "t3": {
     "a": 0,
     "i": 0
    },
    "tc": {
     "a": 1,
     "i": 1
    },
    "tl": {
     "a": 0,
     "i": 0
    },
    "ro": 0,
    "rd": 1,
    "rt": 1,
    "as": 1,
    "br": 1,
    "bp": 0,
    "tf": 0,
    "tco": 0,
    "mt": 0,
    "fc": 0,
    "fr": 1,
    "va": 6,
    "pm": -10
   },
   {
    "idJugador": "2816296",
    "titular": true,
    "dorsal": "23",
    "nombre": "RIBEIROS CARREIRAS, JOAO",
    "seg": 1610,
    "pt": 7,
    "t2": {
     "a": 0,
     "i": 1
    },
    "t3": {
     "a": 2,
     "i": 9
    },
    "tc": {
     "a": 2,
     "i": 10
    },
    "tl": {
     "a": 1,
     "i": 2
    },
    "ro": 0,
    "rd": 2,
    "rt": 2,
    "as": 3,
    "br": 0,
    "bp": 3,
    "tf": 0,
    "tco": 0,
    "mt": 0,
    "fc": 3,
    "fr": 1,
    "va": -2,
    "pm": -23
   },
   {
    "idJugador": "2248492",
    "titular": false,
    "dorsal": "36",
    "nombre": "CARRETERO GONZALEZ, RODRIGO",
    "seg": 1114,
    "pt": 4,
    "t2": {
     "a": 1,
     "i": 2
    },
    "t3": {
     "a": 0,
     "i": 4
    },
    "tc": {
     "a": 1,
     "i": 6
    },
    "tl": {
     "a": 2,
     "i": 2
    },
    "ro": 0,
    "rd": 0,
    "rt": 0,
    "as": 1,
    "br": 0,
    "bp": 0,
    "tf": 0,
    "tco": 0,
    "mt": 0,
    "fc": 0,
    "fr": 1,
    "va": 1,
    "pm": -5
   },
   {
    "idJugador": "2222125",
    "titular": false,
    "dorsal": "44",
    "nombre": "GALLEGO CONTRERAS, ALEJANDRO",
    "seg": 703,
    "pt": 0,
    "t2": {
     "a": 0,
     "i": 1
    },
    "t3": {
     "a": 0,
     "i": 0
    },
    "tc": {
     "a": 0,
     "i": 1
    },
    "tl": {
     "a": 0,
     "i": 0
    },
    "ro": 0,
    "rd": 1,
    "rt": 1,
    "as": 0,
    "br": 0,
    "bp": 0,
    "tf": 0,
    "tco": 0,
    "mt": 0,
    "fc": 1,
    "fr": 0,
    "va": -1,
    "pm": -2
   },
   {
    "idJugador": "2816299",
    "titular": true,
    "dorsal": "77",
    "nombre": "GEDEAO YIMBU, MIGUEL",
    "seg": 2008,
    "pt": 8,
    "t2": {
     "a": 3,
     "i": 8
    },
    "t3": {
     "a": 0,
     "i": 0
    },
    "tc": {
     "a": 3,
     "i": 8
    },
    "tl": {
     "a": 2,
     "i": 5
    },
    "ro": 3,
    "rd": 5,
    "rt": 8,
    "as": 0,
    "br": 1,
    "bp": 8,
    "tf": 3,
    "tco": 0,
    "mt": 0,
    "fc": 4,
    "fr": 4,
    "va": 4,
    "pm": -16
   }
  ],
  "visitante": [
   {
    "idJugador": "2760531",
    "titular": true,
    "dorsal": "4",
    "nombre": "ANDRADE CORREIA E SILVA, HUGO FRANCISCO",
    "seg": 1647,
    "pt": 20,
    "t2": {
     "a": 4,
     "i": 5
    },
    "t3": {
     "a": 4,
     "i": 7
    },
    "tc": {
     "a": 8,
     "i": 12
    },
    "tl": {
     "a": 0,
     "i": 1
    },
    "ro": 0,
    "rd": 3,
    "rt": 3,
    "as": 7,
    "br": 1,
    "bp": 5,
    "tf": 0,
    "tco": 0,
    "mt": 0,
    "fc": 4,
    "fr": 1,
    "va": 18,
    "pm": 26
   },
   {
    "idJugador": "1636820",
    "titular": true,
    "dorsal": "5",
    "nombre": "FREIRE DELTIO, RICARDO",
    "seg": 1465,
    "pt": 13,
    "t2": {
     "a": 3,
     "i": 5
    },
    "t3": {
     "a": 2,
     "i": 2
    },
    "tc": {
     "a": 5,
     "i": 7
    },
    "tl": {
     "a": 1,
     "i": 1
    },
    "ro": 1,
    "rd": 4,
    "rt": 5,
    "as": 3,
    "br": 1,
    "bp": 0,
    "tf": 0,
    "tco": 0,
    "mt": 0,
    "fc": 4,
    "fr": 1,
    "va": 17,
    "pm": 12
   },
   {
    "idJugador": "2069542",
    "titular": true,
    "dorsal": "8",
    "nombre": "ROMERO NARANJO, RAFAEL",
    "seg": 533,
    "pt": 2,
    "t2": {
     "a": 1,
     "i": 3
    },
    "t3": {
     "a": 0,
     "i": 0
    },
    "tc": {
     "a": 1,
     "i": 3
    },
    "tl": {
     "a": 0,
     "i": 0
    },
    "ro": 0,
    "rd": 3,
    "rt": 3,
    "as": 0,
    "br": 0,
    "bp": 1,
    "tf": 0,
    "tco": 0,
    "mt": 0,
    "fc": 0,
    "fr": 2,
    "va": 4,
    "pm": 1
   },
   {
    "idJugador": "1518834",
    "titular": false,
    "dorsal": "10",
    "nombre": "ÁLVAREZ RICO, ANDRÉS",
    "seg": 929,
    "pt": 10,
    "t2": {
     "a": 3,
     "i": 6
    },
    "t3": {
     "a": 1,
     "i": 2
    },
    "tc": {
     "a": 4,
     "i": 8
    },
    "tl": {
     "a": 1,
     "i": 2
    },
    "ro": 2,
    "rd": 2,
    "rt": 4,
    "as": 2,
    "br": 0,
    "bp": 3,
    "tf": 0,
    "tco": 0,
    "mt": 0,
    "fc": 3,
    "fr": 1,
    "va": 6,
    "pm": -7
   },
   {
    "idJugador": "2573616",
    "titular": false,
    "dorsal": "11",
    "nombre": "GIL VARGAS, GONZALO",
    "seg": 42,
    "pt": 2,
    "t2": {
     "a": 1,
     "i": 1
    },
    "t3": {
     "a": 0,
     "i": 0
    },
    "tc": {
     "a": 1,
     "i": 1
    },
    "tl": {
     "a": 0,
     "i": 0
    },
    "ro": 0,
    "rd": 0,
    "rt": 0,
    "as": 0,
    "br": 0,
    "bp": 0,
    "tf": 0,
    "tco": 0,
    "mt": 0,
    "fc": 0,
    "fr": 0,
    "va": 2,
    "pm": 2
   },
   {
    "idJugador": "2199747",
    "titular": false,
    "dorsal": "13",
    "nombre": "VICENTE FERNANDEZ, ALFONSO",
    "seg": 748,
    "pt": 2,
    "t2": {
     "a": 1,
     "i": 1
    },
    "t3": {
     "a": 0,
     "i": 2
    },
    "tc": {
     "a": 1,
     "i": 3
    },
    "tl": {
     "a": 0,
     "i": 0
    },
    "ro": 0,
    "rd": 2,
    "rt": 2,
    "as": 1,
    "br": 1,
    "bp": 3,
    "tf": 0,
    "tco": 0,
    "mt": 0,
    "fc": 2,
    "fr": 1,
    "va": 0,
    "pm": 4
   },
   {
    "idJugador": "2590769",
    "titular": false,
    "dorsal": "16",
    "nombre": "GOMEZ MORENO, PABLO",
    "seg": 243,
    "pt": 0,
    "t2": {
     "a": 0,
     "i": 2
    },
    "t3": {
     "a": 0,
     "i": 0
    },
    "tc": {
     "a": 0,
     "i": 2
    },
    "tl": {
     "a": 0,
     "i": 0
    },
    "ro": 0,
    "rd": 0,
    "rt": 0,
    "as": 0,
    "br": 0,
    "bp": 1,
    "tf": 0,
    "tco": 1,
    "mt": 0,
    "fc": 0,
    "fr": 2,
    "va": -1,
    "pm": -3
   },
   {
    "idJugador": "2267017",
    "titular": true,
    "dorsal": "17",
    "nombre": "LATORRE SANCHEZ, JOAQUIN",
    "seg": 1907,
    "pt": 2,
    "t2": {
     "a": 1,
     "i": 3
    },
    "t3": {
     "a": 0,
     "i": 1
    },
    "tc": {
     "a": 1,
     "i": 4
    },
    "tl": {
     "a": 0,
     "i": 2
    },
    "ro": 0,
    "rd": 7,
    "rt": 7,
    "as": 3,
    "br": 2,
    "bp": 3,
    "tf": 0,
    "tco": 1,
    "mt": 0,
    "fc": 1,
    "fr": 2,
    "va": 7,
    "pm": 13
   },
   {
    "idJugador": "2201855",
    "titular": false,
    "dorsal": "19",
    "nombre": "RODRIGUEZ TORRERO, ADRIAN",
    "seg": 1721,
    "pt": 17,
    "t2": {
     "a": 7,
     "i": 8
    },
    "t3": {
     "a": 1,
     "i": 4
    },
    "tc": {
     "a": 8,
     "i": 12
    },
    "tl": {
     "a": 0,
     "i": 0
    },
    "ro": 2,
    "rd": 5,
    "rt": 7,
    "as": 0,
    "br": 0,
    "bp": 1,
    "tf": 0,
    "tco": 1,
    "mt": 0,
    "fc": 4,
    "fr": 0,
    "va": 15,
    "pm": 12
   },
   {
    "idJugador": "2201760",
    "titular": false,
    "dorsal": "30",
    "nombre": "GONZÁLEZ PALOMO, ÁLVARO",
    "seg": 1134,
    "pt": 9,
    "t2": {
     "a": 0,
     "i": 1
    },
    "t3": {
     "a": 3,
     "i": 6
    },
    "tc": {
     "a": 3,
     "i": 7
    },
    "tl": {
     "a": 0,
     "i": 1
    },
    "ro": 0,
    "rd": 2,
    "rt": 2,
    "as": 4,
    "br": 3,
    "bp": 1,
    "tf": 0,
    "tco": 0,
    "mt": 0,
    "fc": 2,
    "fr": 0,
    "va": 10,
    "pm": 16
   },
   {
    "idJugador": "2818143",
    "titular": true,
    "dorsal": "92",
    "nombre": "VIDAL, BASTIEN VALENTIN OTXOA",
    "seg": 1631,
    "pt": 6,
    "t2": {
     "a": 2,
     "i": 10
    },
    "t3": {
     "a": 0,
     "i": 0
    },
    "tc": {
     "a": 2,
     "i": 10
    },
    "tl": {
     "a": 2,
     "i": 3
    },
    "ro": 3,
    "rd": 3,
    "rt": 6,
    "as": 0,
    "br": 4,
    "bp": 2,
    "tf": 2,
    "tco": 0,
    "mt": 1,
    "fc": 4,
    "fr": 3,
    "va": 6,
    "pm": 14
   }
  ],
  "cuartos": [
   {
    "periodo": "1º C",
    "local": 21,
    "visitante": 14
   },
   {
    "periodo": "2º C",
    "local": 10,
    "visitante": 20
   },
   {
    "periodo": "3º C",
    "local": 13,
    "visitante": 25
   },
   {
    "periodo": "4º C",
    "local": 21,
    "visitante": 24
   }
  ]
 }
}