{
 "id": "2342090",
 "temporada": "2023",
 "grupo": "B-B",
 "jornada": "Jornada 22(10/03/2024)",
 "equipoLocal": {
  "id": "922861",
  "nombre": "C.D. BASKET GLOBALCAJA QUINTANAR"
 },
 "equipoVisitante": {
  "id": "921919",
  "nombre": "CB ARIDANE"
 },
 "resultado": "60-68",
 "disputado": true,
 "descargado": "2026-07-17T14:57:33.731Z",
 "boxscore": {
  "local": [
   {
    "idJugador": "1978802",
    "titular": false,
    "dorsal": "5",
    "nombre": "IBAÑEZ TEJERO, JOSE LUIS",
    "seg": 1927,
    "pt": 24,
    "t2": {
     "a": 10,
     "i": 13
    },
    "t3": {
     "a": 1,
     "i": 6
    },
    "tc": {
     "a": 11,
     "i": 19
    },
    "tl": {
     "a": 1,
     "i": 1
    },
    "ro": 0,
    "rd": 1,
    "rt": 1,
    "as": 0,
    "br": 2,
    "bp": 0,
    "tf": 0,
    "tco": 0,
    "mt": 0,
    "fc": 3,
    "fr": 2,
    "va": 18,
    "pm": 0
   },
   {
    "idJugador": "2557718",
    "titular": false,
    "dorsal": "7",
    "nombre": "VAL GUTIERREZ, SERGIO",
    "seg": 981,
    "pt": 2,
    "t2": {
     "a": 1,
     "i": 5
    },
    "t3": {
     "a": 0,
     "i": 1
    },
    "tc": {
     "a": 1,
     "i": 6
    },
    "tl": {
     "a": 0,
     "i": 0
    },
    "ro": 0,
    "rd": 2,
    "rt": 2,
    "as": 0,
    "br": 0,
    "bp": 1,
    "tf": 0,
    "tco": 1,
    "mt": 0,
    "fc": 1,
    "fr": 0,
    "va": -3,
    "pm": 4
   },
   {
    "idJugador": "2587177",
    "titular": true,
    "dorsal": "8",
    "nombre": "IBARLUCEA LAVIN, DIEGO",
    "seg": 1861,
    "pt": 3,
    "t2": {
     "a": 1,
     "i": 2
    },
    "t3": {
     "a": 0,
     "i": 4
    },
    "tc": {
     "a": 1,
     "i": 6
    },
    "tl": {
     "a": 1,
     "i": 1
    },
    "ro": 0,
    "rd": 2,
    "rt": 2,
    "as": 0,
    "br": 0,
    "bp": 0,
    "tf": 0,
    "tco": 1,
    "mt": 0,
    "fc": 4,
    "fr": 1,
    "va": -3,
    "pm": -5
   },
   {
    "idJugador": "2642903",
    "titular": true,
    "dorsal": "9",
    "nombre": "HROVAT, URBAN",
    "seg": 1885,
    "pt": 7,
    "t2": {
     "a": 2,
     "i": 7
    },
    "t3": {
     "a": 1,
     "i": 5
    },
    "tc": {
     "a": 3,
     "i": 12
    },
    "tl": {
     "a": 0,
     "i": 0
    },
    "ro": 0,
    "rd": 4,
    "rt": 4,
    "as": 6,
    "br": 1,
    "bp": 1,
    "tf": 0,
    "tco": 1,
    "mt": 0,
    "fc": 3,
    "fr": 0,
    "va": 5,
    "pm": -14
   },
   {
    "idJugador": "2009710",
    "titular": false,
    "dorsal": "12",
    "nombre": "MIJE BENITEZ, MANUEL",
    "seg": 1086,
    "pt": 4,
    "t2": {
     "a": 2,
     "i": 5
    },
    "t3": {
     "a": 0,
     "i": 0
    },
    "tc": {
     "a": 2,
     "i": 5
    },
    "tl": {
     "a": 0,
     "i": 0
    },
    "ro": 1,
    "rd": 5,
    "rt": 6,
    "as": 1,
    "br": 0,
    "bp": 1,
    "tf": 1,
    "tco": 1,
    "mt": 0,
    "fc": 3,
    "fr": 0,
    "va": 5,
    "pm": 0
   },
   {
    "idJugador": "1519988",
    "titular": true,
    "dorsal": "15",
    "nombre": "DEUS VERA, RODRIGO",
    "seg": 1454,
    "pt": 6,
    "t2": {
     "a": 2,
     "i": 3
    },
    "t3": {
     "a": 0,
     "i": 2
    },
    "tc": {
     "a": 2,
     "i": 5
    },
    "tl": {
     "a": 2,
     "i": 2
    },
    "ro": 2,
    "rd": 2,
    "rt": 4,
    "as": 0,
    "br": 1,
    "bp": 2,
    "tf": 0,
    "tco": 1,
    "mt": 0,
    "fc": 2,
    "fr": 3,
    "va": 7,
    "pm": -10
   },
   {
    "idJugador": "2219955",
    "titular": true,
    "dorsal": "23",
    "nombre": "DIOP, PAPE ALIOUNE",
    "seg": 872,
    "pt": 4,
    "t2": {
     "a": 2,
     "i": 4
    },
    "t3": {
     "a": 0,
     "i": 1
    },
    "tc": {
     "a": 2,
     "i": 5
    },
    "tl": {
     "a": 0,
     "i": 0
    },
    "ro": 0,
    "rd": 2,
    "rt": 2,
    "as": 0,
    "br": 1,
    "bp": 0,
    "tf": 0,
    "tco": 0,
    "mt": 0,
    "fc": 2,
    "fr": 1,
    "va": 3,
    "pm": -9
   },
   {
    "idJugador": "2642904",
    "titular": true,
    "dorsal": "29",
    "nombre": "ARTMAN, GUY",
    "seg": 1934,
    "pt": 10,
    "t2": {
     "a": 3,
     "i": 7
    },
    "t3": {
     "a": 1,
     "i": 5
    },
    "tc": {
     "a": 4,
     "i": 12
    },
    "tl": {
     "a": 1,
     "i": 2
    },
    "ro": 0,
    "rd": 5,
    "rt": 5,
    "as": 2,
    "br": 4,
    "bp": 1,
    "tf": 0,
    "tco": 1,
    "mt": 0,
    "fc": 5,
    "fr": 3,
    "va": 9,
    "pm": -6
   }
  ],
  "visitante": [
   {
    "idJugador": "2480929",
    "titular": true,
    "dorsal": "0",
    "nombre": "NEWSON, XAVIER TIRREL",
    "seg": 1804,
    "pt": 17,
    "t2": {
     "a": 7,
     "i": 15
    },
    "t3": {
     "a": 0,
     "i": 1
    },
    "tc": {
     "a": 7,
     "i": 16
    },
    "tl": {
     "a": 3,
     "i": 3
    },
    "ro": 2,
    "rd": 1,
    "rt": 3,
    "as": 0,
    "br": 0,
    "bp": 2,
    "tf": 0,
    "tco": 0,
    "mt": 0,
    "fc": 1,
    "fr": 3,
    "va": 11,
    "pm": 10
   },
   {
    "idJugador": "2352358",
    "titular": false,
    "dorsal": "6",
    "nombre": "RAMON FERNANDEZ DE ARROYABE, ALEX",
    "seg": 1536,
    "pt": 6,
    "t2": {
     "a": 0,
     "i": 2
    },
    "t3": {
     "a": 2,
     "i": 8
    },
    "tc": {
     "a": 2,
     "i": 10
    },
    "tl": {
     "a": 0,
     "i": 0
    },
    "ro": 1,
    "rd": 2,
    "rt": 3,
    "as": 4,
    "br": 1,
    "bp": 5,
    "tf": 0,
    "tco": 1,
    "mt": 0,
    "fc": 0,
    "fr": 1,
    "va": 2,
    "pm": 5
   },
   {
    "idJugador": "2177775",
    "titular": true,
    "dorsal": "7",
    "nombre": "GONZÁLEZ CHÁVEZ, JAVIER",
    "seg": 1635,
    "pt": 6,
    "t2": {
     "a": 1,
     "i": 2
    },
    "t3": {
     "a": 1,
     "i": 4
    },
    "tc": {
     "a": 2,
     "i": 6
    },
    "tl": {
     "a": 1,
     "i": 2
    },
    "ro": 0,
    "rd": 5,
    "rt": 5,
    "as": 5,
    "br": 0,
    "bp": 3,
    "tf": 0,
    "tco": 0,
    "mt": 0,
    "fc": 0,
    "fr": 1,
    "va": 9,
    "pm": 8
   },
   {
    "idJugador": "1595217",
    "titular": false,
    "dorsal": "9",
    "nombre": "PARRONDO CASTRO, JORGE",
    "seg": 1234,
    "pt": 10,
    "t2": {
     "a": 4,
     "i": 7
    },
    "t3": {
     "a": 0,
     "i": 0
    },
    "tc": {
     "a": 4,
     "i": 7
    },
    "tl": {
     "a": 2,
     "i": 2
    },
    "ro": 2,
    "rd": 6,
    "rt": 8,
    "as": 0,
    "br": 0,
    "bp": 1,
    "tf": 0,
    "tco": 0,
    "mt": 0,
    "fc": 1,
    "fr": 1,
    "va": 14,
    "pm": -4
   },
   {
    "idJugador": "2061381",
    "titular": true,
    "dorsal": "10",
    "nombre": "BALSELLS PLAZA, ORIOL",
    "seg": 1750,
    "pt": 16,
    "t2": {
     "a": 2,
     "i": 3
    },
    "t3": {
     "a": 2,
     "i": 8
    },
    "tc": {
     "a": 4,
     "i": 11
    },
    "tl": {
     "a": 6,
     "i": 8
    },
    "ro": 1,
    "rd": 6,
    "rt": 7,
    "as": 6,
    "br": 1,
    "bp": 1,
    "tf": 0,
    "tco": 0,
    "mt": 0,
    "fc": 1,
    "fr": 8,
    "va": 27,
    "pm": 13
   },
   {
    "idJugador": "2349443",
    "titular": false,
    "dorsal": "11",
    "nombre": "GUEYE, SERIGNE MODOU",
    "seg": 443,
    "pt": 0,
    "t2": {
     "a": 0,
     "i": 0
    },
    "t3": {
     "a": 0,
     "i": 0
    },
    "tc": {
     "a": 0,
     "i": 0
    },
    "tl": {
     "a": 0,
     "i": 0
    },
    "ro": 2,
    "rd": 3,
    "rt": 5,
    "as": 0,
    "br": 0,
    "bp": 0,
    "tf": 2,
    "tco": 0,
    "mt": 0,
    "fc": 0,
    "fr": 0,
    "va": 7,
    "pm": 1
   },
   {
    "idJugador": "2823134",
    "titular": true,
    "dorsal": "12",
    "nombre": "TRAORE, ADAMA",
    "seg": 1649,
    "pt": 7,
    "t2": {
     "a": 3,
     "i": 3
    },
    "t3": {
     "a": 0,
     "i": 0
    },
    "tc": {
     "a": 3,
     "i": 3
    },
    "tl": {
     "a": 1,
     "i": 3
    },
    "ro": 3,
    "rd": 5,
    "rt": 8,
    "as": 0,
    "br": 2,
    "bp": 2,
    "tf": 4,
    "tco": 0,
    "mt": 1,
    "fc": 4,
    "fr": 5,
    "va": 18,
    "pm": 12
   },
   {
    "idJugador": "2163473",
    "titular": false,
    "dorsal": "16",
    "nombre": "SANCHEZ PEREZ, DIEGO",
    "seg": 632,
    "pt": 2,
    "t2": {
     "a": 1,
     "i": 3
    },
    "t3": {
     "a": 0,
     "i": 0
    },
    "tc": {
     "a": 1,
     "i": 3
    },
    "tl": {
     "a": 0,
     "i": 2
    },
    "ro": 0,
    "rd": 1,
    "rt": 1,
    "as": 0,
    "br": 0,
    "bp": 2,
    "tf": 0,
    "tco": 0,
    "mt": 0,
    "fc": 2,
    "fr": 1,
    "va": -4,
    "pm": -4
   },
   {
    "idJugador": "1534544",
    "titular": false,
    "dorsal": "33",
    "nombre": "RIVEROL DE LAS CASAS, KILIAN JOSE",
    "seg": 913,
    "pt": 2,
    "t2": {
     "a": 0,
     "i": 1
    },
    "t3": {
     "a": 0,
     "i": 3
    },
    "tc": {
     "a": 0,
     "i": 4
    },
    "tl": {
     "a": 2,
     "i": 2
    },
    "ro": 1,
    "rd": 2,
    "rt": 3,
    "as": 0,
    "br": 0,
    "bp": 2,
    "tf": 0,
    "tco": 0,
    "mt": 0,
    "fc": 1,
    "fr": 2,
    "va": 0,
    "pm": -3
   },
   {
    "idJugador": "2801452",
    "titular": true,
    "dorsal": "63",
    "nombre": "WRIGHT, THOMAS JAY",
    "seg": 404,
    "pt": 2,
    "t2": {
     "a": 0,
     "i": 0
    },
    "t3": {
     "a": 0,
     "i": 0
    },
    "tc": {
     "a": 0,
     "i": 0
    },
    "tl": {
     "a": 2,
     "i": 2
    },
    "ro": 2,
    "rd": 3,
    "rt": 5,
    "as": 1,
    "br": 0,
    "bp": 0,
    "tf": 0,
    "tco": 0,
    "mt": 0,
    "fc": 0,
    "fr": 1,
    "va": 9,
    "pm": 2
   }
  ],
  "cuartos": [
   {
    "periodo": "1º C",
    "local": 12,
    "visitante": 21
   },
   {
    "periodo": "2º C",
    "local": 17,
    "visitante": 14
   },
   {
    "periodo": "3º C",
    "local": 18,
    "visitante": 20
   },
   {
    "periodo": "4º C",
    "local": 13,
    "visitante": 13
   }
  ]
 }
}