{
 "id": "2484665",
 "temporada": "2025",
 "grupo": "E-A",
 "jornada": "Jornada 20(01/03/2026)",
 "equipoLocal": {
  "id": "981164",
  "nombre": "CEMALU ALDAIA"
 },
 "equipoVisitante": {
  "id": "982154",
  "nombre": "CB MORVEDRE"
 },
 "resultado": "73-68",
 "disputado": true,
 "descargado": "2026-07-17T07:18:54.215Z",
 "boxscore": {
  "local": [
   {
    "idJugador": "2032916",
    "titular": true,
    "dorsal": "4",
    "nombre": "CISNEROS RUIZ, MARIO",
    "seg": 534,
    "pt": 0,
    "t2": {
     "a": 0,
     "i": 0
    },
    "t3": {
     "a": 0,
     "i": 2
    },
    "tc": {
     "a": 0,
     "i": 2
    },
    "tl": {
     "a": 0,
     "i": 0
    },
    "ro": 0,
    "rd": 1,
    "rt": 1,
    "as": 0,
    "br": 0,
    "bp": 0,
    "tf": 0,
    "tco": 0,
    "mt": 0,
    "fc": 0,
    "fr": 1,
    "va": 0,
    "pm": 0
   },
   {
    "idJugador": "1504277",
    "titular": false,
    "dorsal": "6",
    "nombre": "SANCHEZ DE LA IGLESIA, ANGEL",
    "seg": 804,
    "pt": 11,
    "t2": {
     "a": 1,
     "i": 1
    },
    "t3": {
     "a": 3,
     "i": 4
    },
    "tc": {
     "a": 4,
     "i": 5
    },
    "tl": {
     "a": 0,
     "i": 0
    },
    "ro": 0,
    "rd": 5,
    "rt": 5,
    "as": 0,
    "br": 0,
    "bp": 0,
    "tf": 0,
    "tco": 0,
    "mt": 0,
    "fc": 4,
    "fr": 0,
    "va": 11,
    "pm": 21
   },
   {
    "idJugador": "1504770",
    "titular": false,
    "dorsal": "8",
    "nombre": "HERNANDEZ BENACHES, SERGIO",
    "seg": 1388,
    "pt": 14,
    "t2": {
     "a": 1,
     "i": 5
    },
    "t3": {
     "a": 4,
     "i": 6
    },
    "tc": {
     "a": 5,
     "i": 11
    },
    "tl": {
     "a": 0,
     "i": 0
    },
    "ro": 1,
    "rd": 2,
    "rt": 3,
    "as": 1,
    "br": 0,
    "bp": 1,
    "tf": 0,
    "tco": 0,
    "mt": 0,
    "fc": 3,
    "fr": 0,
    "va": 8,
    "pm": -9
   },
   {
    "idJugador": "1626093",
    "titular": true,
    "dorsal": "10",
    "nombre": "CARRION BALLESTER, SERGIO",
    "seg": 1165,
    "pt": 4,
    "t2": {
     "a": 0,
     "i": 0
    },
    "t3": {
     "a": 0,
     "i": 6
    },
    "tc": {
     "a": 0,
     "i": 6
    },
    "tl": {
     "a": 4,
     "i": 4
    },
    "ro": 0,
    "rd": 2,
    "rt": 2,
    "as": 0,
    "br": 2,
    "bp": 1,
    "tf": 0,
    "tco": 0,
    "mt": 0,
    "fc": 1,
    "fr": 3,
    "va": 3,
    "pm": -11
   },
   {
    "idJugador": "2336206",
    "titular": true,
    "dorsal": "13",
    "nombre": "SOLBES SORIANO, ANTONIO",
    "seg": 1300,
    "pt": 0,
    "t2": {
     "a": 0,
     "i": 3
    },
    "t3": {
     "a": 0,
     "i": 2
    },
    "tc": {
     "a": 0,
     "i": 5
    },
    "tl": {
     "a": 0,
     "i": 2
    },
    "ro": 1,
    "rd": 3,
    "rt": 4,
    "as": 0,
    "br": 0,
    "bp": 1,
    "tf": 0,
    "tco": 1,
    "mt": 0,
    "fc": 3,
    "fr": 2,
    "va": -5,
    "pm": 8
   },
   {
    "idJugador": "1585974",
    "titular": false,
    "dorsal": "14",
    "nombre": "CARRION BALLESTER, RICARDO",
    "seg": 1248,
    "pt": 4,
    "t2": {
     "a": 2,
     "i": 5
    },
    "t3": {
     "a": 0,
     "i": 1
    },
    "tc": {
     "a": 2,
     "i": 6
    },
    "tl": {
     "a": 0,
     "i": 0
    },
    "ro": 0,
    "rd": 4,
    "rt": 4,
    "as": 2,
    "br": 0,
    "bp": 1,
    "tf": 0,
    "tco": 0,
    "mt": 0,
    "fc": 2,
    "fr": 0,
    "va": 3,
    "pm": 8
   },
   {
    "idJugador": "1805625",
    "titular": false,
    "dorsal": "17",
    "nombre": "GONZALEZ BRU, MARCOS",
    "seg": 720,
    "pt": 1,
    "t2": {
     "a": 0,
     "i": 2
    },
    "t3": {
     "a": 0,
     "i": 1
    },
    "tc": {
     "a": 0,
     "i": 3
    },
    "tl": {
     "a": 1,
     "i": 2
    },
    "ro": 0,
    "rd": 1,
    "rt": 1,
    "as": 1,
    "br": 0,
    "bp": 2,
    "tf": 0,
    "tco": 0,
    "mt": 0,
    "fc": 4,
    "fr": 1,
    "va": -6,
    "pm": -16
   },
   {
    "idJugador": "2343041",
    "titular": false,
    "dorsal": "21",
    "nombre": "MEDINA LERMA, RAFEL",
    "seg": 942,
    "pt": 5,
    "t2": {
     "a": 2,
     "i": 3
    },
    "t3": {
     "a": 0,
     "i": 0
    },
    "tc": {
     "a": 2,
     "i": 3
    },
    "tl": {
     "a": 1,
     "i": 2
    },
    "ro": 2,
    "rd": 3,
    "rt": 5,
    "as": 1,
    "br": 1,
    "bp": 1,
    "tf": 1,
    "tco": 0,
    "mt": 0,
    "fc": 3,
    "fr": 1,
    "va": 8,
    "pm": 0
   },
   {
    "idJugador": "2257487",
    "titular": false,
    "dorsal": "24",
    "nombre": "PINA RODRIGUEZ, EYDAN",
    "seg": 179,
    "pt": 0,
    "t2": {
     "a": 0,
     "i": 1
    },
    "t3": {
     "a": 0,
     "i": 0
    },
    "tc": {
     "a": 0,
     "i": 1
    },
    "tl": {
     "a": 0,
     "i": 0
    },
    "ro": 0,
    "rd": 0,
    "rt": 0,
    "as": 0,
    "br": 0,
    "bp": 0,
    "tf": 0,
    "tco": 0,
    "mt": 0,
    "fc": 0,
    "fr": 0,
    "va": -1,
    "pm": -4
   },
   {
    "idJugador": "1994971",
    "titular": true,
    "dorsal": "41",
    "nombre": "BLASCO MANZANO, FRANCISCO JAVIER",
    "seg": 1786,
    "pt": 10,
    "t2": {
     "a": 4,
     "i": 6
    },
    "t3": {
     "a": 0,
     "i": 2
    },
    "tc": {
     "a": 4,
     "i": 8
    },
    "tl": {
     "a": 2,
     "i": 2
    },
    "ro": 0,
    "rd": 4,
    "rt": 4,
    "as": 3,
    "br": 1,
    "bp": 6,
    "tf": 0,
    "tco": 0,
    "mt": 0,
    "fc": 0,
    "fr": 3,
    "va": 11,
    "pm": 17
   },
   {
    "idJugador": "1626092",
    "titular": true,
    "dorsal": "53",
    "nombre": "HORTELANO ESCRIBA, CARLOS",
    "seg": 1934,
    "pt": 24,
    "t2": {
     "a": 5,
     "i": 10
    },
    "t3": {
     "a": 3,
     "i": 6
    },
    "tc": {
     "a": 8,
     "i": 16
    },
    "tl": {
     "a": 5,
     "i": 5
    },
    "ro": 4,
    "rd": 8,
    "rt": 12,
    "as": 1,
    "br": 0,
    "bp": 3,
    "tf": 1,
    "tco": 0,
    "mt": 0,
    "fc": 2,
    "fr": 7,
    "va": 32,
    "pm": 11
   }
  ],
  "visitante": [
   {
    "idJugador": "1685233",
    "titular": true,
    "dorsal": "0",
    "nombre": "GONZALEZ SOLER, ALEJANDRO",
    "seg": 716,
    "pt": 0,
    "t2": {
     "a": 0,
     "i": 3
    },
    "t3": {
     "a": 0,
     "i": 3
    },
    "tc": {
     "a": 0,
     "i": 6
    },
    "tl": {
     "a": 0,
     "i": 0
    },
    "ro": 1,
    "rd": 2,
    "rt": 3,
    "as": 1,
    "br": 1,
    "bp": 1,
    "tf": 0,
    "tco": 0,
    "mt": 0,
    "fc": 0,
    "fr": 1,
    "va": -1,
    "pm": 7
   },
   {
    "idJugador": "1760182",
    "titular": true,
    "dorsal": "5",
    "nombre": "MERENCIO FERRER, JONATHAN",
    "seg": 1013,
    "pt": 2,
    "t2": {
     "a": 1,
     "i": 4
    },
    "t3": {
     "a": 0,
     "i": 0
    },
    "tc": {
     "a": 1,
     "i": 4
    },
    "tl": {
     "a": 0,
     "i": 2
    },
    "ro": 2,
    "rd": 3,
    "rt": 5,
    "as": 0,
    "br": 0,
    "bp": 1,
    "tf": 1,
    "tco": 0,
    "mt": 0,
    "fc": 1,
    "fr": 1,
    "va": 2,
    "pm": -7
   },
   {
    "idJugador": "2335904",
    "titular": false,
    "dorsal": "6",
    "nombre": "ARNAIZ VEGA, SERGIO",
    "seg": 1174,
    "pt": 10,
    "t2": {
     "a": 3,
     "i": 3
    },
    "t3": {
     "a": 1,
     "i": 4
    },
    "tc": {
     "a": 4,
     "i": 7
    },
    "tl": {
     "a": 1,
     "i": 2
    },
    "ro": 0,
    "rd": 0,
    "rt": 0,
    "as": 1,
    "br": 0,
    "bp": 3,
    "tf": 0,
    "tco": 0,
    "mt": 0,
    "fc": 3,
    "fr": 5,
    "va": 6,
    "pm": -14
   },
   {
    "idJugador": "1687185",
    "titular": true,
    "dorsal": "7",
    "nombre": "FOS CERVERA, BORJA",
    "seg": 867,
    "pt": 1,
    "t2": {
     "a": 0,
     "i": 0
    },
    "t3": {
     "a": 0,
     "i": 2
    },
    "tc": {
     "a": 0,
     "i": 2
    },
    "tl": {
     "a": 1,
     "i": 2
    },
    "ro": 2,
    "rd": 1,
    "rt": 3,
    "as": 1,
    "br": 0,
    "bp": 1,
    "tf": 0,
    "tco": 0,
    "mt": 0,
    "fc": 3,
    "fr": 1,
    "va": -1,
    "pm": -1
   },
   {
    "idJugador": "2335903",
    "titular": false,
    "dorsal": "9",
    "nombre": "ARNAIZ VEGA, JAIME",
    "seg": 1415,
    "pt": 10,
    "t2": {
     "a": 1,
     "i": 3
    },
    "t3": {
     "a": 2,
     "i": 7
    },
    "tc": {
     "a": 3,
     "i": 10
    },
    "tl": {
     "a": 2,
     "i": 3
    },
    "ro": 0,
    "rd": 5,
    "rt": 5,
    "as": 3,
    "br": 1,
    "bp": 2,
    "tf": 0,
    "tco": 0,
    "mt": 0,
    "fc": 2,
    "fr": 2,
    "va": 9,
    "pm": -20
   },
   {
    "idJugador": "1995206",
    "titular": false,
    "dorsal": "10",
    "nombre": "COMPANY LOPEZ, AARON",
    "seg": 1080,
    "pt": 11,
    "t2": {
     "a": 2,
     "i": 4
    },
    "t3": {
     "a": 2,
     "i": 4
    },
    "tc": {
     "a": 4,
     "i": 8
    },
    "tl": {
     "a": 1,
     "i": 1
    },
    "ro": 1,
    "rd": 1,
    "rt": 2,
    "as": 0,
    "br": 0,
    "bp": 0,
    "tf": 0,
    "tco": 1,
    "mt": 0,
    "fc": 3,
    "fr": 1,
    "va": 7,
    "pm": -3
   },
   {
    "idJugador": "1839763",
    "titular": true,
    "dorsal": "11",
    "nombre": "BUSTAMANTE CONTRERAS, PEDRO",
    "seg": 1418,
    "pt": 11,
    "t2": {
     "a": 3,
     "i": 8
    },
    "t3": {
     "a": 1,
     "i": 4
    },
    "tc": {
     "a": 4,
     "i": 12
    },
    "tl": {
     "a": 2,
     "i": 4
    },
    "ro": 1,
    "rd": 4,
    "rt": 5,
    "as": 2,
    "br": 0,
    "bp": 0,
    "tf": 0,
    "tco": 0,
    "mt": 0,
    "fc": 0,
    "fr": 4,
    "va": 12,
    "pm": 4
   },
   {
    "idJugador": "2813036",
    "titular": false,
    "dorsal": "31",
    "nombre": "MARTÍNEZ TEJERO, JOSÉ ANTONIO",
    "seg": 927,
    "pt": 5,
    "t2": {
     "a": 0,
     "i": 1
    },
    "t3": {
     "a": 1,
     "i": 4
    },
    "tc": {
     "a": 1,
     "i": 5
    },
    "tl": {
     "a": 2,
     "i": 2
    },
    "ro": 0,
    "rd": 3,
    "rt": 3,
    "as": 0,
    "br": 5,
    "bp": 0,
    "tf": 0,
    "tco": 0,
    "mt": 0,
    "fc": 0,
    "fr": 1,
    "va": 10,
    "pm": 8
   },
   {
    "idJugador": "2100605",
    "titular": false,
    "dorsal": "47",
    "nombre": "ANTONI RODRIGUEZ, MIGUEL",
    "seg": 1145,
    "pt": 6,
    "t2": {
     "a": 3,
     "i": 8
    },
    "t3": {
     "a": 0,
     "i": 0
    },
    "tc": {
     "a": 3,
     "i": 8
    },
    "tl": {
     "a": 0,
     "i": 2
    },
    "ro": 2,
    "rd": 2,
    "rt": 4,
    "as": 1,
    "br": 1,
    "bp": 1,
    "tf": 0,
    "tco": 1,
    "mt": 1,
    "fc": 0,
    "fr": 1,
    "va": 5,
    "pm": 4
   },
   {
    "idJugador": "2225299",
    "titular": true,
    "dorsal": "52",
    "nombre": "CORNEJO GONZALEZ, MARCOS",
    "seg": 1007,
    "pt": 2,
    "t2": {
     "a": 1,
     "i": 3
    },
    "t3": {
     "a": 0,
     "i": 1
    },
    "tc": {
     "a": 1,
     "i": 4
    },
    "tl": {
     "a": 0,
     "i": 0
    },
    "ro": 1,
    "rd": 0,
    "rt": 1,
    "as": 1,
    "br": 1,
    "bp": 0,
    "tf": 0,
    "tco": 0,
    "mt": 0,
    "fc": 5,
    "fr": 2,
    "va": -1,
    "pm": 5
   },
   {
    "idJugador": "2164737",
    "titular": false,
    "dorsal": "86",
    "nombre": "DOMINGUEZ ALEIXANDRE, SERGIO",
    "seg": 1238,
    "pt": 10,
    "t2": {
     "a": 4,
     "i": 10
    },
    "t3": {
     "a": 0,
     "i": 1
    },
    "tc": {
     "a": 4,
     "i": 11
    },
    "tl": {
     "a": 2,
     "i": 4
    },
    "ro": 7,
    "rd": 4,
    "rt": 11,
    "as": 0,
    "br": 0,
    "bp": 0,
    "tf": 0,
    "tco": 0,
    "mt": 1,
    "fc": 1,
    "fr": 3,
    "va": 14,
    "pm": -8
   }
  ],
  "cuartos": [
   {
    "periodo": "1º C",
    "local": 21,
    "visitante": 15
   },
   {
    "periodo": "2º C",
    "local": 9,
    "visitante": 22
   },
   {
    "periodo": "3º C",
    "local": 31,
    "visitante": 7
   },
   {
    "periodo": "4º C",
    "local": 12,
    "visitante": 24
   }
  ]
 }
}